[
  {
    "model": "feeder.accessrole",
    "pk": "ADMIN",
    "fields": {
      "created_at": "2024-03-06T20:13:51.761Z",
      "updated_at": "2024-03-06T20:13:51.761Z",
      "name": "Админ",
      "description": "Полный доступ"
    }
  },
  {
    "model": "feeder.accessrole",
    "pk": "SENIOR",
    "fields": {
      "created_at": "2024-03-06T20:13:51.761Z",
      "updated_at": "2024-03-06T20:13:51.761Z",
      "name": "Сташий смены",
      "description": "Все кроме бана и назначения прав доступа"
    }
  },
  {
    "model": "feeder.accessrole",
    "pk": "CAT",
    "fields": {
      "created_at": "2024-03-06T20:13:51.761Z",
      "updated_at": "2024-03-06T20:13:51.761Z",
      "name": "Кот",
      "description": "Все кроме бана, назначения прав доступа, редактирования кастомных столбцов, множественных операций, перевода в другую службу и редактирования групповых бейджей"
    }
  },
  {
    "model": "feeder.accessrole",
    "pk": "DIRECTION_HEAD",
    "fields": {
      "created_at": "2024-03-06T20:13:51.761Z",
      "updated_at": "2024-03-06T20:13:51.761Z",
      "name": "Руководитель локации",
      "description": "Просмотр и редактирование волонтеров своих локаций, кроме назначения прав доступа, множественных операций, перевода в другую службу и редактирования групповых бейджей"
    }
  }
]
